{
    "layers":  {
                   "humanoid":  [
                                    {
                                        "dyeable":  {

                                                    },
                                        "texture":  "minecraft:leather_cit_base/9246834"
                                    },
                                    {
                                        "texture":  "minecraft:leather_cit/9246834"
                                    }
                                ],
                   "humanoid_leggings":  [
                                             {
                                                 "dyeable":  {

                                                             },
                                                 "texture":  "minecraft:leather_cit_base/9246834"
                                             },
                                             {
                                                 "texture":  "minecraft:leather_cit/9246834"
                                             }
                                         ]
               }
}
