{"format_version":"1.9.0","credit":"made_by_bubblesducky","textures":{"0":"merch/ednahair","particle":"merch/ednahair"},"elements":[{"from":[3,0,12],"to":[13,8,13],"rotation":{"angle":0,"axis":"y","origin":[7,0,6]},"faces":{"north":{"uv":[0,8,10,16],"texture":"#0"},"east":{"uv":[2,9,3,16],"texture":"#0"},"south":{"uv":[0,8,10,16],"texture":"#0"},"west":{"uv":[8,8,9,16],"texture":"#0"},"up":{"uv":[10,1,0,0],"texture":"#0"},"down":{"uv":[10,0,0,1],"texture":"#0"}}},{"from":[3,4,3],"to":[13,8,4],"rotation":{"angle":0,"axis":"y","origin":[7,0,-3]},"faces":{"north":{"uv":[10,6,14,16],"rotation":90,"texture":"#0"},"east":{"uv":[4,12,5,16],"texture":"#0"},"south":{"uv":[10,6,14,16],"rotation":90,"texture":"#0"},"west":{"uv":[4,11,5,15],"texture":"#0"},"up":{"uv":[11,16,10,6],"rotation":90,"texture":"#0"},"down":{"uv":[13,16,14,6],"rotation":90,"texture":"#0"}}},{"from":[3,8,4],"to":[13,9,12],"rotation":{"angle":0,"axis":"y","origin":[7,8,5]},"faces":{"north":{"uv":[10,0,0,1],"texture":"#0"},"east":{"uv":[14,6,15,14],"rotation":90,"texture":"#0"},"south":{"uv":[10,0,0,1],"texture":"#0"},"west":{"uv":[12,6,13,14],"rotation":90,"texture":"#0"},"up":{"uv":[10,8,0,0],"texture":"#0"},"down":{"uv":[10,0,0,8],"texture":"#0"}}},{"from":[13,0,4],"to":[14,8,12],"rotation":{"angle":0,"axis":"y","origin":[8,0,5]},"faces":{"north":{"uv":[2,9,3,16],"texture":"#0"},"east":{"uv":[0,9,8,16],"texture":"#0"},"south":{"uv":[7,9,8,16],"texture":"#0"},"west":{"uv":[0,8,8,16],"texture":"#0"},"up":{"uv":[15,14,14,6],"texture":"#0"},"down":{"uv":[15,6,14,14],"texture":"#0"}}},{"from":[2,0,4],"to":[3,8,12],"rotation":{"angle":0,"axis":"y","origin":[8,0,5]},"faces":{"north":{"uv":[3,9,2,16],"texture":"#0"},"east":{"uv":[2,8,10,16],"texture":"#0"},"south":{"uv":[4,8,3,16],"texture":"#0"},"west":{"uv":[8,9,0,16],"texture":"#0"},"up":{"uv":[14,14,15,6],"texture":"#0"},"down":{"uv":[14,6,15,14],"texture":"#0"}}},{"from":[8.5,-0.5,2.9],"to":[13.5,4.5,2.91],"rotation":{"angle":0,"axis":"y","origin":[11.5,2.5,1.4]},"faces":{"north":{"uv":[10,0,16,6],"texture":"#0"},"south":{"uv":[10,0,16,6],"texture":"#0"}}},{"from":[7.5,1.5,2.9],"to":[8.5,2.5,2.91],"rotation":{"angle":0,"axis":"y","origin":[6.5,4.5,1.4]},"faces":{"north":{"uv":[12,0,13,1],"texture":"#0"},"south":{"uv":[12,0,13,1],"texture":"#0"}}},{"from":[2.5,-0.5,2.9],"to":[7.5,4.5,2.91],"rotation":{"angle":0,"axis":"y","origin":[5.5,2.5,1.4]},"faces":{"north":{"uv":[10,0,16,6],"texture":"#0"},"south":{"uv":[10,0,16,6],"texture":"#0"}}}],"display":{"thirdperson_righthand":{"rotation":[38.25,0,0],"translation":[0,1,0],"scale":[0.6,0.6,0.6]},"thirdperson_lefthand":{"rotation":[38.25,0,0],"translation":[0,1,0],"scale":[0.6,0.6,0.6]},"ground":{"translation":[0,4.25,0],"scale":[0.5,0.5,0.5]},"gui":{"rotation":[8,157,0],"translation":[0,4.25,0]},"head":{"translation":[0,7.25,-0.25],"scale":[1.6,1.6,1.6]},"fixed":{"translation":[0,0,-4.5]},"on_shelf":{"rotation":[0,180,0]}},"groups":[{"name":"group","origin":[8,8,8],"color":0,"children":[0,1,2,3,4,5,6,7]}]}
